debugsnap
