Metadata-Version: 2.1
Name: debugsnap
Version: 0.1.8
Summary: A tool to save and load a snapshot of a Python debugging environment.
Home-page: https://github.com/v4lue4dded/debugsnap
Author: v4lue4dded
Author-email: v4lue4dded@gmail.com
Classifier: Programming Language :: Python :: 3
Classifier: License :: OSI Approved :: MIT License
Classifier: Operating System :: OS Independent
Requires-Python: >=3.6
License-File: LICENSE
